{
  "id": "pfs2.s1-21",
  "parent": "pfs2.season1-layout-s1-19",
  "description": "1-21 Mistress of the Maze",
  "defaultChronicleLocation": "modules/pfs-chronicle-generator/assets/chronicles/pfs2/season1/1-21-MistressoftheMazeChronicle.pdf",
  "parameters": {
    "Items": {
      "strikeout_item_lines": {
        "type": "choice",
        "description": "Item line text to be struck out",
        "choices": [
          "5\u20136",
          "SUBTIER",
          "7\u20138"
        ],
        "example": "5\u20136"
      }
    }
  },
  "presets": {
    "strikeout_item": {
      "canvas": "items",
      "color": "black",
      "x": 0.5,
      "x2": 95
    },
    "item.line.5\u20136": {
      "y": 20.0,
      "y2": 24.7
    },
    "item.line.SUBTIER": {
      "y": 73.6,
      "y2": 84.9
    },
    "item.line.7\u20138": {
      "y": 67.9,
      "y2": 72.4
    }
  },
  "content": [
    {
      "type": "choice",
      "choices": "param:strikeout_item_lines",
      "content": {
        "5\u20136": [
          {
            "type": "strikeout",
            "presets": [
              "strikeout_item",
              "item.line.5\u20136"
            ]
          }
        ],
        "SUBTIER": [
          {
            "type": "strikeout",
            "presets": [
              "strikeout_item",
              "item.line.SUBTIER"
            ]
          }
        ],
        "7\u20138": [
          {
            "type": "strikeout",
            "presets": [
              "strikeout_item",
              "item.line.7\u20138"
            ]
          }
        ]
      }
    }
  ]
}
